terminal_layout/__init__.py
terminal_layout/ctl.py
terminal_layout/log.py
terminal_layout/types.py
terminal_layout/ansi/__init__.py
terminal_layout/ansi/back.py
terminal_layout/ansi/font.py
terminal_layout/ansi/fore.py
terminal_layout/ansi/style.py
terminal_layout/extensions/__init__.py
terminal_layout/extensions/choice/__init__.py
terminal_layout/extensions/choice/choice.py
terminal_layout/extensions/input/__init__.py
terminal_layout/extensions/input/_old.py
terminal_layout/extensions/input/input_ex.py
terminal_layout/extensions/progress/__init__.py
terminal_layout/extensions/progress/loading.py
terminal_layout/extensions/progress/progress.py
terminal_layout/extensions/scroll/__init__.py
terminal_layout/extensions/scroll/scroll.py
terminal_layout/helper/__init__.py
terminal_layout/helper/class_helper.py
terminal_layout/helper/helper.py
terminal_layout/readkey/__init__.py
terminal_layout/readkey/event.py
terminal_layout/readkey/key.py
terminal_layout/readkey/linux.py
terminal_layout/readkey/listener.py
terminal_layout/readkey/windows.py
terminal_layout/view/__init__.py
terminal_layout/view/base.py
terminal_layout/view/layout.py
terminal_layout/view/params.py
terminal_layout/view/text_view.py
terminal_layout/view/util.py
terminal_layout-3.0.0.dist-info/LICENSE
terminal_layout-3.0.0.dist-info/METADATA
terminal_layout-3.0.0.dist-info/WHEEL
terminal_layout-3.0.0.dist-info/top_level.txt
terminal_layout-3.0.0.dist-info/RECORD
