Metadata-Version: 2.1
Name: terminal_layout
Version: 3.0.0
Summary: The project help you to quickly build layouts in terminal (命令行ui布局工具)
Author-email: gojuukaze <ikaze_email@163.com>
Project-URL: Homepage, https://github.com/gojuukaze/terminal_layout
Project-URL: Bug Tracker, https://github.com/gojuukaze/terminal_layout/issues
Project-URL: Documentation, https://doc.ikaze.cn/terminal_layout
Classifier: Programming Language :: Python :: 3
Classifier: Operating System :: OS Independent
Classifier: Environment :: Console
Classifier: License :: OSI Approved :: GNU General Public License v3 (GPLv3)
Classifier: Development Status :: 5 - Production/Stable
Classifier: Topic :: Terminals
Requires-Python: >=3.5
License-File: LICENSE
